dev_pipeline_cmake-0.4.1.dist-info/DESCRIPTION.rst
dev_pipeline_cmake-0.4.1.dist-info/METADATA
dev_pipeline_cmake-0.4.1.dist-info/RECORD
dev_pipeline_cmake-0.4.1.dist-info/WHEEL
dev_pipeline_cmake-0.4.1.dist-info/entry_points.txt
dev_pipeline_cmake-0.4.1.dist-info/metadata.json
dev_pipeline_cmake-0.4.1.dist-info/top_level.txt
devpipeline_cmake/__init__.py
devpipeline_cmake/cmake.py
