Metadata-Version: 2.0
Name: dev-pipeline-cmake
Version: 0.4.1
Summary: cmake plugin for dev-pipeline
Home-page: https://github.com/dev-pipeline/dev-pipeline-cmake
Author: Stephen Newell
Author-email: UNKNOWN
License: BSD-2
Platform: UNKNOWN
Classifier: Development Status :: 2 - Pre-Alpha
Classifier: Environment :: Plugins
Classifier: Intended Audience :: Developers
Classifier: License :: OSI Approved :: BSD License
Classifier: Topic :: Software Development
Classifier: Topic :: Software Development :: Build Tools
Classifier: Topic :: Utilities
Requires-Dist: dev-pipeline-build (>=0.4.0)
Requires-Dist: dev-pipeline-core (>=0.4.0)
